barcode/__init__.py
barcode/base.py
barcode/codex.py
barcode/ean.py
barcode/errors.py
barcode/isxn.py
barcode/itf.py
barcode/pybarcode.py
barcode/upc.py
barcode/version.py
barcode/writer.py
barcode/charsets/__init__.py
barcode/charsets/code128.py
barcode/charsets/code39.py
barcode/charsets/ean.py
barcode/charsets/itf.py
barcode/charsets/upc.py
barcode/fonts/DejaVuSansMono.ttf
parcode-1.0.0.dist-info/LICENCE
parcode-1.0.0.dist-info/METADATA
parcode-1.0.0.dist-info/WHEEL
parcode-1.0.0.dist-info/entry_points.txt
parcode-1.0.0.dist-info/top_level.txt
parcode-1.0.0.dist-info/RECORD
